{
    "language": "en", 
    "label": 1, 
    "tokens": [], 
    "entities": [
        {
            "mentions": [
                {
                    "text": {
                        "content": "Hes", 
                        "beginOffset": -1
                    }, 
                    "type": "COMMON"
                }
            ], 
            "metadata": {}, 
            "type": "PERSON", 
            "name": "Hes", 
            "salience": 0.36647353
        }, 
        {
            "mentions": [
                {
                    "text": {
                        "content": "people", 
                        "beginOffset": -1
                    }, 
                    "type": "COMMON"
                }
            ], 
            "metadata": {}, 
            "type": "PERSON", 
            "name": "people", 
            "salience": 0.21873732
        }, 
        {
            "mentions": [
                {
                    "text": {
                        "content": "reason", 
                        "beginOffset": -1
                    }, 
                    "type": "COMMON"
                }
            ], 
            "metadata": {}, 
            "type": "OTHER", 
            "name": "reason", 
            "salience": 0.17086679
        }, 
        {
            "mentions": [
                {
                    "text": {
                        "content": "im", 
                        "beginOffset": -1
                    }, 
                    "type": "COMMON"
                }
            ], 
            "metadata": {}, 
            "type": "OTHER", 
            "name": "im", 
            "salience": 0.05068274
        }, 
        {
            "mentions": [
                {
                    "text": {
                        "content": "him.", 
                        "beginOffset": -1
                    }, 
                    "type": "COMMON"
                }
            ], 
            "metadata": {}, 
            "type": "OTHER", 
            "name": "him.", 
            "salience": 0.042258013
        }, 
        {
            "mentions": [
                {
                    "text": {
                        "content": "adoption", 
                        "beginOffset": -1
                    }, 
                    "type": "COMMON"
                }
            ], 
            "metadata": {}, 
            "type": "OTHER", 
            "name": "adoption", 
            "salience": 0.032553833
        }, 
        {
            "mentions": [
                {
                    "text": {
                        "content": "hes", 
                        "beginOffset": -1
                    }, 
                    "type": "COMMON"
                }
            ], 
            "metadata": {}, 
            "type": "OTHER", 
            "name": "hes", 
            "salience": 0.025441946
        }, 
        {
            "mentions": [
                {
                    "text": {
                        "content": "someone", 
                        "beginOffset": -1
                    }, 
                    "type": "COMMON"
                }
            ], 
            "metadata": {}, 
            "type": "PERSON", 
            "name": "someone", 
            "salience": 0.024728836
        }, 
        {
            "mentions": [
                {
                    "text": {
                        "content": "attention", 
                        "beginOffset": -1
                    }, 
                    "type": "COMMON"
                }
            ], 
            "metadata": {}, 
            "type": "OTHER", 
            "name": "attention", 
            "salience": 0.020336578
        }, 
        {
            "mentions": [
                {
                    "text": {
                        "content": "toilet train", 
                        "beginOffset": -1
                    }, 
                    "type": "COMMON"
                }
            ], 
            "metadata": {}, 
            "type": "OTHER", 
            "name": "toilet train", 
            "salience": 0.019989956
        }, 
        {
            "mentions": [
                {
                    "text": {
                        "content": "boy", 
                        "beginOffset": -1
                    }, 
                    "type": "COMMON"
                }
            ], 
            "metadata": {}, 
            "type": "PERSON", 
            "name": "boy", 
            "salience": 0.0139652295
        }, 
        {
            "mentions": [
                {
                    "text": {
                        "content": "home", 
                        "beginOffset": -1
                    }, 
                    "type": "COMMON"
                }
            ], 
            "metadata": {}, 
            "type": "LOCATION", 
            "name": "home", 
            "salience": 0.0139652295
        }
    ], 
    "documentSentiment": {
        "magnitude": 2.7, 
        "score": 0.3
    }, 
    "sentences": [
        {
            "text": {
                "content": "Hes very playful , love it when people hug him .", 
                "beginOffset": -1
            }, 
            "sentiment": {
                "magnitude": 0.9, 
                "score": 0.9
            }
        }, 
        {
            "text": {
                "content": "reason that im giving him.for adoption is because i dont have much time for him . he needs someone that can give him all the attention he needs .", 
                "beginOffset": -1
            }, 
            "sentiment": {
                "magnitude": 0.1, 
                "score": 0.1
            }
        }, 
        {
            "text": {
                "content": "hes very clingy and hes also toilet train .", 
                "beginOffset": -1
            }, 
            "sentiment": {
                "magnitude": 0.6, 
                "score": -0.6
            }
        }, 
        {
            "text": {
                "content": "looking for loving adopter who can gv this boy a lovely home .", 
                "beginOffset": -1
            }, 
            "sentiment": {
                "magnitude": 0.9, 
                "score": 0.9
            }
        }
    ], 
    "raw_content": "Hes very playful , love it when people hug him . reason that im giving him.for adoption is because i dont have much time for him . he needs someone that can give him all the attention he needs . hes very clingy and hes also toilet train . looking for loving adopter who can gv this boy a lovely home . ", 
    "categories": []
}