{
    "language": "en", 
    "label": 4, 
    "tokens": [], 
    "entities": [
        {
            "mentions": [
                {
                    "text": {
                        "content": "Jenny", 
                        "beginOffset": -1
                    }, 
                    "type": "PROPER"
                }
            ], 
            "metadata": {}, 
            "type": "PERSON", 
            "name": "Jenny", 
            "salience": 0.8076273
        }, 
        {
            "mentions": [
                {
                    "text": {
                        "content": "dog", 
                        "beginOffset": -1
                    }, 
                    "type": "COMMON"
                }
            ], 
            "metadata": {}, 
            "type": "OTHER", 
            "name": "dog", 
            "salience": 0.05045542
        }, 
        {
            "mentions": [
                {
                    "text": {
                        "content": "house", 
                        "beginOffset": -1
                    }, 
                    "type": "COMMON"
                }, 
                {
                    "text": {
                        "content": "house", 
                        "beginOffset": -1
                    }, 
                    "type": "COMMON"
                }
            ], 
            "metadata": {}, 
            "type": "LOCATION", 
            "name": "house", 
            "salience": 0.04256704
        }, 
        {
            "mentions": [
                {
                    "text": {
                        "content": "living", 
                        "beginOffset": -1
                    }, 
                    "type": "COMMON"
                }
            ], 
            "metadata": {}, 
            "type": "OTHER", 
            "name": "living", 
            "salience": 0.019843996
        }, 
        {
            "mentions": [
                {
                    "text": {
                        "content": "manja", 
                        "beginOffset": -1
                    }, 
                    "type": "COMMON"
                }
            ], 
            "metadata": {}, 
            "type": "OTHER", 
            "name": "manja", 
            "salience": 0.006246301
        }, 
        {
            "mentions": [
                {
                    "text": {
                        "content": "dog", 
                        "beginOffset": -1
                    }, 
                    "type": "COMMON"
                }
            ], 
            "metadata": {}, 
            "type": "OTHER", 
            "name": "dog", 
            "salience": 0.005919447
        }, 
        {
            "mentions": [
                {
                    "text": {
                        "content": "tail", 
                        "beginOffset": -1
                    }, 
                    "type": "COMMON"
                }
            ], 
            "metadata": {}, 
            "type": "OTHER", 
            "name": "tail", 
            "salience": 0.0058748764
        }, 
        {
            "mentions": [
                {
                    "text": {
                        "content": "car", 
                        "beginOffset": -1
                    }, 
                    "type": "COMMON"
                }
            ], 
            "metadata": {}, 
            "type": "CONSUMER_GOOD", 
            "name": "car", 
            "salience": 0.0058748764
        }, 
        {
            "mentions": [
                {
                    "text": {
                        "content": "dog", 
                        "beginOffset": -1
                    }, 
                    "type": "COMMON"
                }
            ], 
            "metadata": {}, 
            "type": "OTHER", 
            "name": "dog", 
            "salience": 0.005826711
        }, 
        {
            "mentions": [
                {
                    "text": {
                        "content": "house", 
                        "beginOffset": -1
                    }, 
                    "type": "COMMON"
                }
            ], 
            "metadata": {}, 
            "type": "LOCATION", 
            "name": "house", 
            "salience": 0.0050469264
        }, 
        {
            "mentions": [
                {
                    "text": {
                        "content": "hell", 
                        "beginOffset": -1
                    }, 
                    "type": "COMMON"
                }
            ], 
            "metadata": {}, 
            "type": "OTHER", 
            "name": "hell", 
            "salience": 0.003988368
        }, 
        {
            "mentions": [
                {
                    "text": {
                        "content": "mom", 
                        "beginOffset": -1
                    }, 
                    "type": "COMMON"
                }
            ], 
            "metadata": {}, 
            "type": "PERSON", 
            "name": "mom", 
            "salience": 0.003988368
        }, 
        {
            "mentions": [
                {
                    "text": {
                        "content": "dad", 
                        "beginOffset": -1
                    }, 
                    "type": "COMMON"
                }
            ], 
            "metadata": {}, 
            "type": "PERSON", 
            "name": "dad", 
            "salience": 0.003988368
        }, 
        {
            "mentions": [
                {
                    "text": {
                        "content": "gate", 
                        "beginOffset": -1
                    }, 
                    "type": "COMMON"
                }
            ], 
            "metadata": {}, 
            "type": "OTHER", 
            "name": "gate", 
            "salience": 0.003956001
        }, 
        {
            "mentions": [
                {
                    "text": {
                        "content": "infront", 
                        "beginOffset": -1
                    }, 
                    "type": "COMMON"
                }
            ], 
            "metadata": {}, 
            "type": "OTHER", 
            "name": "infront", 
            "salience": 0.003956001
        }, 
        {
            "mentions": [
                {
                    "text": {
                        "content": "road", 
                        "beginOffset": -1
                    }, 
                    "type": "COMMON"
                }
            ], 
            "metadata": {}, 
            "type": "LOCATION", 
            "name": "road", 
            "salience": 0.0036538003
        }, 
        {
            "mentions": [
                {
                    "text": {
                        "content": "rain", 
                        "beginOffset": -1
                    }, 
                    "type": "COMMON"
                }
            ], 
            "metadata": {}, 
            "type": "OTHER", 
            "name": "rain", 
            "salience": 0.0036538003
        }, 
        {
            "mentions": [
                {
                    "text": {
                        "content": "collar", 
                        "beginOffset": -1
                    }, 
                    "type": "COMMON"
                }
            ], 
            "metadata": {}, 
            "type": "CONSUMER_GOOD", 
            "name": "collar", 
            "salience": 0.002750259
        }, 
        {
            "mentions": [
                {
                    "text": {
                        "content": "bath", 
                        "beginOffset": -1
                    }, 
                    "type": "COMMON"
                }
            ], 
            "metadata": {}, 
            "type": "OTHER", 
            "name": "bath", 
            "salience": 0.002750259
        }, 
        {
            "mentions": [
                {
                    "text": {
                        "content": "vaccine", 
                        "beginOffset": -1
                    }, 
                    "type": "COMMON"
                }
            ], 
            "metadata": {}, 
            "type": "OTHER", 
            "name": "vaccine", 
            "salience": 0.002750259
        }, 
        {
            "mentions": [
                {
                    "text": {
                        "content": "warmth", 
                        "beginOffset": -1
                    }, 
                    "type": "COMMON"
                }
            ], 
            "metadata": {}, 
            "type": "OTHER", 
            "name": "warmth", 
            "salience": 0.0019205961
        }, 
        {
            "mentions": [
                {
                    "text": {
                        "content": "photos", 
                        "beginOffset": -1
                    }, 
                    "type": "COMMON"
                }
            ], 
            "metadata": {}, 
            "type": "WORK_OF_ART", 
            "name": "photos", 
            "salience": 0.0019166538
        }, 
        {
            "mentions": [
                {
                    "text": {
                        "content": "home", 
                        "beginOffset": -1
                    }, 
                    "type": "COMMON"
                }
            ], 
            "metadata": {}, 
            "type": "LOCATION", 
            "name": "home", 
            "salience": 0.0018971174
        }, 
        {
            "mentions": [
                {
                    "text": {
                        "content": "heart bastards", 
                        "beginOffset": -1
                    }, 
                    "type": "COMMON"
                }
            ], 
            "metadata": {}, 
            "type": "PERSON", 
            "name": "heart bastards", 
            "salience": 0.0012080623
        }, 
        {
            "mentions": [
                {
                    "text": {
                        "content": "anyone", 
                        "beginOffset": -1
                    }, 
                    "type": "COMMON"
                }
            ], 
            "metadata": {}, 
            "type": "PERSON", 
            "name": "anyone", 
            "salience": 0.0012063124
        }, 
        {
            "mentions": [
                {
                    "text": {
                        "content": "PS", 
                        "beginOffset": -1
                    }, 
                    "type": "PROPER"
                }
            ], 
            "metadata": {}, 
            "type": "CONSUMER_GOOD", 
            "name": "PS", 
            "salience": 0.0011328612
        }
    ], 
    "documentSentiment": {
        "magnitude": 4.1, 
        "score": 0.1
    }, 
    "sentences": [
        {
            "text": {
                "content": "Jenny is a very sweet and gentle dog.", 
                "beginOffset": -1
            }, 
            "sentiment": {
                "magnitude": 0.9, 
                "score": 0.9
            }
        }, 
        {
            "text": {
                "content": "She is a stray living NEAR my house.", 
                "beginOffset": -1
            }, 
            "sentiment": {
                "magnitude": 0, 
                "score": 0
            }
        }, 
        {
            "text": {
                "content": "I have been feeding her since she was born.", 
                "beginOffset": -1
            }, 
            "sentiment": {
                "magnitude": 0, 
                "score": 0
            }
        }, 
        {
            "text": {
                "content": "She will wag her tail and become manja when she sees me or my car.", 
                "beginOffset": -1
            }, 
            "sentiment": {
                "magnitude": 0, 
                "score": 0
            }
        }, 
        {
            "text": {
                "content": "At night she sleeps infront of my gate as if she is guarding us.", 
                "beginOffset": -1
            }, 
            "sentiment": {
                "magnitude": 0.4, 
                "score": 0.4
            }
        }, 
        {
            "text": {
                "content": "If there is any other stray dog approaching my house, she will chase them away.", 
                "beginOffset": -1
            }, 
            "sentiment": {
                "magnitude": 0, 
                "score": 0
            }
        }, 
        {
            "text": {
                "content": "Me and my dad wanted to take her into my house but my mom protest like hell.", 
                "beginOffset": -1
            }, 
            "sentiment": {
                "magnitude": 0.5, 
                "score": -0.5
            }
        }, 
        {
            "text": {
                "content": "She is such a sweet dog and i hate to see her roaming the road, getting wet and cold in the rain, or get bullied by some no heart bastards.", 
                "beginOffset": -1
            }, 
            "sentiment": {
                "magnitude": 0.7, 
                "score": -0.7
            }
        }, 
        {
            "text": {
                "content": "If anyone want to adopt her, please give me time to get her into collar, bath her, deworm her, vaccine her, etc.", 
                "beginOffset": -1
            }, 
            "sentiment": {
                "magnitude": 0.1, 
                "score": 0.1
            }
        }, 
        {
            "text": {
                "content": "She has been spayed.", 
                "beginOffset": -1
            }, 
            "sentiment": {
                "magnitude": 0, 
                "score": 0
            }
        }, 
        {
            "text": {
                "content": "I love her very much and i want her to have a home full of warmth.", 
                "beginOffset": -1
            }, 
            "sentiment": {
                "magnitude": 0.9, 
                "score": 0.9
            }
        }, 
        {
            "text": {
                "content": "Thank you.", 
                "beginOffset": -1
            }, 
            "sentiment": {
                "magnitude": 0, 
                "score": 0
            }
        }, 
        {
            "text": {
                "content": "PS: I will update more photos soon.", 
                "beginOffset": -1
            }, 
            "sentiment": {
                "magnitude": 0.3, 
                "score": 0.3
            }
        }
    ], 
    "raw_content": "Jenny is a very sweet and gentle dog. She is a stray living NEAR my house. I have been feeding her since she was born. She will wag her tail and become manja when she sees me or my car. At night she sleeps infront of my gate as if she is guarding us. If there is any other stray dog approaching my house, she will chase them away. Me and my dad wanted to take her into my house but my mom protest like hell. She is such a sweet dog and i hate to see her roaming the road, getting wet and cold in the rain, or get bullied by some no heart bastards. If anyone want to adopt her, please give me time to get her into collar, bath her, deworm her, vaccine her, etc. She has been spayed. I love her very much and i want her to have a home full of warmth. Thank you. PS: I will update more photos soon. ", 
    "categories": []
}