{
    "language": "en", 
    "label": 1, 
    "tokens": [], 
    "entities": [
        {
            "mentions": [
                {
                    "text": {
                        "content": "people.", 
                        "beginOffset": -1
                    }, 
                    "type": "COMMON"
                }
            ], 
            "metadata": {}, 
            "type": "PERSON", 
            "name": "people.", 
            "salience": 0.42936447
        }, 
        {
            "mentions": [
                {
                    "text": {
                        "content": "attention", 
                        "beginOffset": -1
                    }, 
                    "type": "COMMON"
                }
            ], 
            "metadata": {}, 
            "type": "OTHER", 
            "name": "attention", 
            "salience": 0.18650733
        }, 
        {
            "mentions": [
                {
                    "text": {
                        "content": "friends", 
                        "beginOffset": -1
                    }, 
                    "type": "COMMON"
                }
            ], 
            "metadata": {}, 
            "type": "PERSON", 
            "name": "friends", 
            "salience": 0.18650733
        }, 
        {
            "mentions": [
                {
                    "text": {
                        "content": "walk", 
                        "beginOffset": -1
                    }, 
                    "type": "COMMON"
                }
            ], 
            "metadata": {}, 
            "type": "EVENT", 
            "name": "walk", 
            "salience": 0.112322345
        }, 
        {
            "mentions": [
                {
                    "text": {
                        "content": "leash", 
                        "beginOffset": -1
                    }, 
                    "type": "COMMON"
                }
            ], 
            "metadata": {}, 
            "type": "OTHER", 
            "name": "leash", 
            "salience": 0.085298516
        }
    ], 
    "documentSentiment": {
        "magnitude": 1.3, 
        "score": 0.6
    }, 
    "sentences": [
        {
            "text": {
                "content": "he loves being around people. he loves attention especially your friends that he had never seen before. he loves running, going for a walk, he will never pulls you in his leash.", 
                "beginOffset": -1
            }, 
            "sentiment": {
                "magnitude": 0.9, 
                "score": 0.9
            }
        }, 
        {
            "text": {
                "content": "gentle and yet smart.", 
                "beginOffset": -1
            }, 
            "sentiment": {
                "magnitude": 0.4, 
                "score": 0.4
            }
        }
    ], 
    "raw_content": "he loves being around people. he loves attention especially your friends that he had never seen before. he loves running, going for a walk, he will never pulls you in his leash. gentle and yet smart. ", 
    "categories": []
}