{
    "language": "en", 
    "label": 3, 
    "tokens": [], 
    "entities": [
        {
            "salience": 0.8146375, 
            "mentions": [
                {
                    "text": {
                        "content": "adoption contact", 
                        "beginOffset": -1
                    }, 
                    "type": "COMMON"
                }
            ], 
            "type": "OTHER", 
            "name": "adoption contact", 
            "metadata": {}
        }, 
        {
            "salience": 0.1853625, 
            "mentions": [
                {
                    "text": {
                        "content": ").com", 
                        "beginOffset": -1
                    }, 
                    "type": "PROPER"
                }
            ], 
            "type": "OTHER", 
            "name": ").com", 
            "metadata": {}
        }
    ], 
    "documentSentiment": {
        "magnitude": 0.1, 
        "score": 0.1
    }, 
    "sentences": [
        {
            "text": {
                "content": "for adoption contact me at meowpinkly(at).com", 
                "beginOffset": -1
            }, 
            "sentiment": {
                "magnitude": 0.1, 
                "score": 0.1
            }
        }
    ], 
    "categories": []
}