{
    "Fee": 0, 
    "sentences": [
        {
            "text": {
                "content": "Found her in my yard, meowing for food.", 
                "beginOffset": -1
            }, 
            "sentiment": {
                "magnitude": 0.5, 
                "score": 0.5
            }
        }, 
        {
            "text": {
                "content": "Playful and manja.", 
                "beginOffset": -1
            }, 
            "sentiment": {
                "magnitude": 0.2, 
                "score": 0.2
            }
        }, 
        {
            "text": {
                "content": "I have to hold her still to take photos.", 
                "beginOffset": -1
            }, 
            "sentiment": {
                "magnitude": 0, 
                "score": 0
            }
        }, 
        {
            "text": {
                "content": "Clean and healthy hair, seems like a lost pet.", 
                "beginOffset": -1
            }, 
            "sentiment": {
                "magnitude": 0.4, 
                "score": 0.4
            }
        }, 
        {
            "text": {
                "content": "Location: Bandar Utama BU11.", 
                "beginOffset": -1
            }, 
            "sentiment": {
                "magnitude": 0.1, 
                "score": 0.1
            }
        }
    ], 
    "PhotoAmt": 3.0, 
    "Breed1": 266, 
    "Breed2": 0, 
    "MaturitySize": 1, 
    "Dewormed": 3, 
    "label": 2, 
    "Color1": 1, 
    "entities": [
        {
            "salience": 0.50661683, 
            "mentions": [
                {
                    "text": {
                        "content": "yard", 
                        "beginOffset": -1
                    }, 
                    "type": "COMMON"
                }
            ], 
            "type": "LOCATION", 
            "name": "yard", 
            "metadata": {}
        }, 
        {
            "salience": 0.20889832, 
            "mentions": [
                {
                    "text": {
                        "content": "food", 
                        "beginOffset": -1
                    }, 
                    "type": "COMMON"
                }
            ], 
            "type": "OTHER", 
            "name": "food", 
            "metadata": {}
        }, 
        {
            "salience": 0.07414827, 
            "mentions": [
                {
                    "text": {
                        "content": "photos", 
                        "beginOffset": -1
                    }, 
                    "type": "COMMON"
                }
            ], 
            "type": "WORK_OF_ART", 
            "name": "photos", 
            "metadata": {}
        }, 
        {
            "salience": 0.07014417, 
            "mentions": [
                {
                    "text": {
                        "content": "manja", 
                        "beginOffset": -1
                    }, 
                    "type": "COMMON"
                }
            ], 
            "type": "OTHER", 
            "name": "manja", 
            "metadata": {}
        }, 
        {
            "salience": 0.048935384, 
            "mentions": [
                {
                    "text": {
                        "content": "pet", 
                        "beginOffset": -1
                    }, 
                    "type": "COMMON"
                }
            ], 
            "type": "OTHER", 
            "name": "pet", 
            "metadata": {}
        }, 
        {
            "salience": 0.048802797, 
            "mentions": [
                {
                    "text": {
                        "content": "Location", 
                        "beginOffset": -1
                    }, 
                    "type": "COMMON"
                }
            ], 
            "type": "LOCATION", 
            "name": "Location", 
            "metadata": {}
        }, 
        {
            "salience": 0.022131372, 
            "mentions": [
                {
                    "text": {
                        "content": "hair", 
                        "beginOffset": -1
                    }, 
                    "type": "COMMON"
                }
            ], 
            "type": "OTHER", 
            "name": "hair", 
            "metadata": {}
        }, 
        {
            "salience": 0.020322831, 
            "mentions": [
                {
                    "text": {
                        "content": "Bandar Utama BU11", 
                        "beginOffset": -1
                    }, 
                    "type": "PROPER"
                }
            ], 
            "type": "PERSON", 
            "name": "Bandar Utama BU11", 
            "metadata": {}
        }
    ], 
    "Color3": 0, 
    "Color2": 7, 
    "categories": [], 
    "Gender": 2, 
    "Age": 6, 
    "tokens": [], 
    "FurLength": 1, 
    "Quantity": 1, 
    "language": "en", 
    "Vaccinated": 3, 
    "documentSentiment": {
        "magnitude": 1.3, 
        "score": 0.2
    }, 
    "Sterilized": 3
}