{
    "language": "en", 
    "label": 2, 
    "tokens": [], 
    "entities": [
        {
            "salience": 0.57833356, 
            "mentions": [
                {
                    "text": {
                        "content": "litter box", 
                        "beginOffset": -1
                    }, 
                    "type": "COMMON"
                }
            ], 
            "type": "OTHER", 
            "name": "litter box", 
            "metadata": {}
        }, 
        {
            "salience": 0.42166644, 
            "mentions": [
                {
                    "text": {
                        "content": "food -must neuter", 
                        "beginOffset": -1
                    }, 
                    "type": "COMMON"
                }
            ], 
            "type": "OTHER", 
            "name": "food -must neuter", 
            "metadata": {}
        }
    ], 
    "documentSentiment": {
        "magnitude": 0.9, 
        "score": 0.9
    }, 
    "sentences": [
        {
            "text": {
                "content": "-active, playful and friendly -well trained to use litter box -ok to eat dry and wet food -must neuter when reached 1yr old", 
                "beginOffset": -1
            }, 
            "sentiment": {
                "magnitude": 0.9, 
                "score": 0.9
            }
        }
    ], 
    "categories": []
}