{
    "language": "en", 
    "label": 4, 
    "tokens": [], 
    "entities": [
        {
            "salience": 0.47829854, 
            "mentions": [
                {
                    "text": {
                        "content": "Trixie", 
                        "beginOffset": -1
                    }, 
                    "type": "PROPER"
                }
            ], 
            "type": "PERSON", 
            "name": "Trixie", 
            "metadata": {}
        }, 
        {
            "salience": 0.30321887, 
            "mentions": [
                {
                    "text": {
                        "content": "females", 
                        "beginOffset": -1
                    }, 
                    "type": "COMMON"
                }
            ], 
            "type": "PERSON", 
            "name": "females", 
            "metadata": {}
        }, 
        {
            "salience": 0.2184826, 
            "mentions": [
                {
                    "text": {
                        "content": "Baby", 
                        "beginOffset": -1
                    }, 
                    "type": "PROPER"
                }
            ], 
            "type": "PERSON", 
            "name": "Baby", 
            "metadata": {}
        }
    ], 
    "documentSentiment": {
        "magnitude": 0, 
        "score": 0
    }, 
    "sentences": [
        {
            "text": {
                "content": "Trixie and Baby are both females and are 6 weeks old", 
                "beginOffset": -1
            }, 
            "sentiment": {
                "magnitude": 0, 
                "score": 0
            }
        }
    ], 
    "categories": []
}