{
    "Fee": 0, 
    "sentences": [
        {
            "text": {
                "content": "Chanelle found a home!", 
                "beginOffset": -1
            }, 
            "sentiment": {
                "magnitude": 0.1, 
                "score": 0.1
            }
        }
    ], 
    "PhotoAmt": 10.0, 
    "Breed1": 20, 
    "Breed2": 307, 
    "MaturitySize": 2, 
    "Dewormed": 1, 
    "label": 0, 
    "Color1": 2, 
    "entities": [
        {
            "salience": 0.7176709, 
            "mentions": [
                {
                    "text": {
                        "content": "Chanelle", 
                        "beginOffset": -1
                    }, 
                    "type": "PROPER"
                }
            ], 
            "type": "PERSON", 
            "name": "Chanelle", 
            "metadata": {}
        }, 
        {
            "salience": 0.2823291, 
            "mentions": [
                {
                    "text": {
                        "content": "home", 
                        "beginOffset": -1
                    }, 
                    "type": "COMMON"
                }
            ], 
            "type": "LOCATION", 
            "name": "home", 
            "metadata": {}
        }
    ], 
    "Color3": 0, 
    "Color2": 7, 
    "categories": [], 
    "Gender": 2, 
    "Age": 18, 
    "tokens": [], 
    "FurLength": 1, 
    "Quantity": 1, 
    "language": "en", 
    "Vaccinated": 1, 
    "documentSentiment": {
        "magnitude": 0.1, 
        "score": 0.1
    }, 
    "Sterilized": 1
}