{
    "language": "en", 
    "label": 2, 
    "tokens": [], 
    "entities": [
        {
            "salience": 0.23769084, 
            "mentions": [
                {
                    "text": {
                        "content": "friend", 
                        "beginOffset": -1
                    }, 
                    "type": "COMMON"
                }
            ], 
            "type": "PERSON", 
            "name": "friend", 
            "metadata": {}
        }, 
        {
            "salience": 0.19669326, 
            "mentions": [
                {
                    "text": {
                        "content": "people", 
                        "beginOffset": -1
                    }, 
                    "type": "COMMON"
                }
            ], 
            "type": "PERSON", 
            "name": "people", 
            "metadata": {}
        }, 
        {
            "salience": 0.0974386, 
            "mentions": [
                {
                    "text": {
                        "content": "behalf", 
                        "beginOffset": -1
                    }, 
                    "type": "COMMON"
                }
            ], 
            "type": "OTHER", 
            "name": "behalf", 
            "metadata": {}
        }, 
        {
            "salience": 0.09457024, 
            "mentions": [
                {
                    "text": {
                        "content": "owner", 
                        "beginOffset": -1
                    }, 
                    "type": "COMMON"
                }
            ], 
            "type": "PERSON", 
            "name": "owner", 
            "metadata": {}
        }, 
        {
            "salience": 0.08143779, 
            "mentions": [
                {
                    "text": {
                        "content": "cats", 
                        "beginOffset": -1
                    }, 
                    "type": "COMMON"
                }
            ], 
            "type": "OTHER", 
            "name": "cats", 
            "metadata": {}
        }, 
        {
            "salience": 0.050141603, 
            "mentions": [
                {
                    "text": {
                        "content": "cats", 
                        "beginOffset": -1
                    }, 
                    "type": "COMMON"
                }
            ], 
            "type": "OTHER", 
            "name": "cats", 
            "metadata": {}
        }, 
        {
            "salience": 0.03754073, 
            "mentions": [
                {
                    "text": {
                        "content": "group", 
                        "beginOffset": -1
                    }, 
                    "type": "COMMON"
                }
            ], 
            "type": "PERSON", 
            "name": "group", 
            "metadata": {}
        }, 
        {
            "salience": 0.032042, 
            "mentions": [
                {
                    "text": {
                        "content": "Location", 
                        "beginOffset": -1
                    }, 
                    "type": "COMMON"
                }
            ], 
            "type": "LOCATION", 
            "name": "Location", 
            "metadata": {}
        }, 
        {
            "salience": 0.024976697, 
            "mentions": [
                {
                    "text": {
                        "content": "age range", 
                        "beginOffset": -1
                    }, 
                    "type": "COMMON"
                }
            ], 
            "type": "OTHER", 
            "name": "age range", 
            "metadata": {}
        }, 
        {
            "salience": 0.023495859, 
            "mentions": [
                {
                    "text": {
                        "content": "females", 
                        "beginOffset": -1
                    }, 
                    "type": "COMMON"
                }
            ], 
            "type": "PERSON", 
            "name": "females", 
            "metadata": {}
        }, 
        {
            "salience": 0.022928225, 
            "mentions": [
                {
                    "text": {
                        "content": "males", 
                        "beginOffset": -1
                    }, 
                    "type": "COMMON"
                }
            ], 
            "type": "PERSON", 
            "name": "males", 
            "metadata": {}
        }, 
        {
            "salience": 0.020309512, 
            "mentions": [
                {
                    "text": {
                        "content": "Cats", 
                        "beginOffset": -1
                    }, 
                    "type": "PROPER"
                }
            ], 
            "type": "ORGANIZATION", 
            "name": "Cats", 
            "metadata": {
                "mid": "/m/01yrx", 
                "wikipedia_url": "https://en.wikipedia.org/wiki/Cat"
            }
        }, 
        {
            "salience": 0.0180976, 
            "mentions": [
                {
                    "text": {
                        "content": "Bukit Tinggi", 
                        "beginOffset": -1
                    }, 
                    "type": "PROPER"
                }
            ], 
            "type": "LOCATION", 
            "name": "Bukit Tinggi", 
            "metadata": {
                "mid": "/m/0b9qsl", 
                "wikipedia_url": "https://en.wikipedia.org/wiki/Bukit_Tinggi,_Pahang"
            }
        }, 
        {
            "salience": 0.017669095, 
            "mentions": [
                {
                    "text": {
                        "content": "adopters", 
                        "beginOffset": -1
                    }, 
                    "type": "COMMON"
                }
            ], 
            "type": "PERSON", 
            "name": "adopters", 
            "metadata": {}
        }, 
        {
            "salience": 0.015244702, 
            "mentions": [
                {
                    "text": {
                        "content": "Klang", 
                        "beginOffset": -1
                    }, 
                    "type": "PROPER"
                }
            ], 
            "type": "LOCATION", 
            "name": "Klang", 
            "metadata": {}
        }, 
        {
            "salience": 0.0077651525, 
            "mentions": [
                {
                    "text": {
                        "content": "home", 
                        "beginOffset": -1
                    }, 
                    "type": "COMMON"
                }
            ], 
            "type": "LOCATION", 
            "name": "home", 
            "metadata": {}
        }, 
        {
            "salience": 0.007326052, 
            "mentions": [
                {
                    "text": {
                        "content": "Aina @ aina.", 
                        "beginOffset": -1
                    }, 
                    "type": "PROPER"
                }
            ], 
            "type": "OTHER", 
            "name": "Aina @ aina.", 
            "metadata": {}
        }, 
        {
            "salience": 0.007326052, 
            "mentions": [
                {
                    "text": {
                        "content": "@", 
                        "beginOffset": -1
                    }, 
                    "type": "PROPER"
                }
            ], 
            "type": "OTHER", 
            "name": "@", 
            "metadata": {}
        }, 
        {
            "salience": 0.007305989, 
            "mentions": [
                {
                    "text": {
                        "content": "TQ", 
                        "beginOffset": -1
                    }, 
                    "type": "PROPER"
                }
            ], 
            "type": "PERSON", 
            "name": "TQ", 
            "metadata": {}
        }
    ], 
    "documentSentiment": {
        "magnitude": 1.7, 
        "score": 0
    }, 
    "sentences": [
        {
            "text": {
                "content": "Hi people..", 
                "beginOffset": -1
            }, 
            "sentiment": {
                "magnitude": 0.2, 
                "score": 0.2
            }
        }, 
        {
            "text": {
                "content": "On behalf of my good friend,I'm posting a group of cats that she is currently fostering.There are 4 cats all together,they are siblings.Location is Bukit Tinggi,Klang.", 
                "beginOffset": -1
            }, 
            "sentiment": {
                "magnitude": 0.3, 
                "score": 0.3
            }
        }, 
        {
            "text": {
                "content": "Cats' age range are from 4-6 months old.There are 2 males and 2 females.", 
                "beginOffset": -1
            }, 
            "sentiment": {
                "magnitude": 0.9, 
                "score": -0.9
            }
        }, 
        {
            "text": {
                "content": "New owner must own a cat-friendly home and know how to care for cats.Preferably be adopted together or in pairs.Serious adopters please contact Aina @ aina. or call/msg her @.", 
                "beginOffset": -1
            }, 
            "sentiment": {
                "magnitude": 0.2, 
                "score": 0.2
            }
        }, 
        {
            "text": {
                "content": "TQ.", 
                "beginOffset": -1
            }, 
            "sentiment": {
                "magnitude": 0, 
                "score": 0
            }
        }
    ], 
    "categories": []
}