{
    "language": "en", 
    "label": 2, 
    "tokens": [], 
    "entities": [
        {
            "salience": 0.59569013, 
            "mentions": [
                {
                    "text": {
                        "content": "Macho", 
                        "beginOffset": -1
                    }, 
                    "type": "PROPER"
                }
            ], 
            "type": "PERSON", 
            "name": "Macho", 
            "metadata": {}
        }, 
        {
            "salience": 0.10994244, 
            "mentions": [
                {
                    "text": {
                        "content": "siblings", 
                        "beginOffset": -1
                    }, 
                    "type": "COMMON"
                }
            ], 
            "type": "PERSON", 
            "name": "siblings", 
            "metadata": {}
        }, 
        {
            "salience": 0.095971614, 
            "mentions": [
                {
                    "text": {
                        "content": "Putra Perdana", 
                        "beginOffset": -1
                    }, 
                    "type": "PROPER"
                }
            ], 
            "type": "LOCATION", 
            "name": "Putra Perdana", 
            "metadata": {
                "mid": "/g/1v2gb7x9"
            }
        }, 
        {
            "salience": 0.077511564, 
            "mentions": [
                {
                    "text": {
                        "content": "group", 
                        "beginOffset": -1
                    }, 
                    "type": "COMMON"
                }
            ], 
            "type": "ORGANIZATION", 
            "name": "group", 
            "metadata": {}
        }, 
        {
            "salience": 0.065909296, 
            "mentions": [
                {
                    "text": {
                        "content": "Puchong", 
                        "beginOffset": -1
                    }, 
                    "type": "PROPER"
                }
            ], 
            "type": "LOCATION", 
            "name": "Puchong", 
            "metadata": {
                "mid": "/m/0cxff7", 
                "wikipedia_url": "https://en.wikipedia.org/wiki/Puchong"
            }
        }, 
        {
            "salience": 0.054974947, 
            "mentions": [
                {
                    "text": {
                        "content": "people", 
                        "beginOffset": -1
                    }, 
                    "type": "COMMON"
                }
            ], 
            "type": "PERSON", 
            "name": "people", 
            "metadata": {}
        }
    ], 
    "documentSentiment": {
        "magnitude": 0.2, 
        "score": 0.2
    }, 
    "sentences": [
        {
            "text": {
                "content": "Macho was rescued at Putra Perdana, Puchong wirh his siblings while being abused by a group of people.", 
                "beginOffset": -1
            }, 
            "sentiment": {
                "magnitude": 0.2, 
                "score": 0.2
            }
        }
    ], 
    "categories": []
}