{
    "Fee": 0, 
    "sentences": [
        {
            "text": {
                "content": "Angel is one sweet darling which just got rescued from the cruel street.", 
                "beginOffset": -1
            }, 
            "sentiment": {
                "magnitude": 0, 
                "score": 0
            }
        }, 
        {
            "text": {
                "content": "She is of good nature and is good w children :)", 
                "beginOffset": -1
            }, 
            "sentiment": {
                "magnitude": 0.9, 
                "score": 0.9
            }
        }, 
        {
            "text": {
                "content": "If interested, pls msg, whatsapp or wechat me with your name &amp; location.", 
                "beginOffset": -1
            }, 
            "sentiment": {
                "magnitude": 0, 
                "score": 0
            }
        }, 
        {
            "text": {
                "content": "For outstation, transportation can b arranged w no obligation.", 
                "beginOffset": -1
            }, 
            "sentiment": {
                "magnitude": 0.6, 
                "score": 0.6
            }
        }, 
        {
            "text": {
                "content": "Just hoping to find Angel her forever home sweet home \u2661", 
                "beginOffset": -1
            }, 
            "sentiment": {
                "magnitude": 0.7, 
                "score": 0.7
            }
        }
    ], 
    "PhotoAmt": 1.0, 
    "Breed1": 307, 
    "Breed2": 0, 
    "MaturitySize": 2, 
    "Dewormed": 1, 
    "label": 3, 
    "Color1": 1, 
    "entities": [
        {
            "salience": 0.7579865, 
            "mentions": [
                {
                    "text": {
                        "content": "Angel", 
                        "beginOffset": -1
                    }, 
                    "type": "PROPER"
                }, 
                {
                    "text": {
                        "content": "darling", 
                        "beginOffset": -1
                    }, 
                    "type": "COMMON"
                }
            ], 
            "type": "PERSON", 
            "name": "Angel", 
            "metadata": {}
        }, 
        {
            "salience": 0.06987091, 
            "mentions": [
                {
                    "text": {
                        "content": "street", 
                        "beginOffset": -1
                    }, 
                    "type": "COMMON"
                }
            ], 
            "type": "LOCATION", 
            "name": "street", 
            "metadata": {}
        }, 
        {
            "salience": 0.02949778, 
            "mentions": [
                {
                    "text": {
                        "content": "children", 
                        "beginOffset": -1
                    }, 
                    "type": "COMMON"
                }
            ], 
            "type": "PERSON", 
            "name": "children", 
            "metadata": {}
        }, 
        {
            "salience": 0.023131426, 
            "mentions": [
                {
                    "text": {
                        "content": "nature", 
                        "beginOffset": -1
                    }, 
                    "type": "COMMON"
                }
            ], 
            "type": "OTHER", 
            "name": "nature", 
            "metadata": {}
        }, 
        {
            "salience": 0.021395285, 
            "mentions": [
                {
                    "text": {
                        "content": "name", 
                        "beginOffset": -1
                    }, 
                    "type": "COMMON"
                }
            ], 
            "type": "OTHER", 
            "name": "name", 
            "metadata": {}
        }, 
        {
            "salience": 0.021395285, 
            "mentions": [
                {
                    "text": {
                        "content": "location", 
                        "beginOffset": -1
                    }, 
                    "type": "COMMON"
                }
            ], 
            "type": "LOCATION", 
            "name": "location", 
            "metadata": {}
        }, 
        {
            "salience": 0.017492415, 
            "mentions": [
                {
                    "text": {
                        "content": "home sweet home", 
                        "beginOffset": -1
                    }, 
                    "type": "COMMON"
                }
            ], 
            "type": "OTHER", 
            "name": "home sweet home", 
            "metadata": {}
        }, 
        {
            "salience": 0.016102798, 
            "mentions": [
                {
                    "text": {
                        "content": "obligation", 
                        "beginOffset": -1
                    }, 
                    "type": "COMMON"
                }
            ], 
            "type": "OTHER", 
            "name": "obligation", 
            "metadata": {}
        }, 
        {
            "salience": 0.013829358, 
            "mentions": [
                {
                    "text": {
                        "content": "whatsapp", 
                        "beginOffset": -1
                    }, 
                    "type": "PROPER"
                }
            ], 
            "type": "CONSUMER_GOOD", 
            "name": "whatsapp", 
            "metadata": {
                "mid": "/m/0gwzvs1", 
                "wikipedia_url": "https://en.wikipedia.org/wiki/WhatsApp"
            }
        }, 
        {
            "salience": 0.007589321, 
            "mentions": [
                {
                    "text": {
                        "content": "Angel", 
                        "beginOffset": -1
                    }, 
                    "type": "PROPER"
                }
            ], 
            "type": "PERSON", 
            "name": "Angel", 
            "metadata": {}
        }, 
        {
            "salience": 0.0075352984, 
            "mentions": [
                {
                    "text": {
                        "content": "b", 
                        "beginOffset": -1
                    }, 
                    "type": "COMMON"
                }
            ], 
            "type": "OTHER", 
            "name": "b", 
            "metadata": {}
        }, 
        {
            "salience": 0.0070868004, 
            "mentions": [
                {
                    "text": {
                        "content": "transportation", 
                        "beginOffset": -1
                    }, 
                    "type": "COMMON"
                }
            ], 
            "type": "OTHER", 
            "name": "transportation", 
            "metadata": {}
        }, 
        {
            "salience": 0.0070868004, 
            "mentions": [
                {
                    "text": {
                        "content": "outstation", 
                        "beginOffset": -1
                    }, 
                    "type": "COMMON"
                }
            ], 
            "type": "OTHER", 
            "name": "outstation", 
            "metadata": {}
        }
    ], 
    "Color3": 7, 
    "Color2": 2, 
    "categories": [], 
    "Gender": 2, 
    "Age": 3, 
    "tokens": [], 
    "FurLength": 2, 
    "Quantity": 1, 
    "language": "en", 
    "Vaccinated": 2, 
    "documentSentiment": {
        "magnitude": 2.3, 
        "score": 0.4
    }, 
    "Sterilized": 2
}