{
    "language": "en", 
    "label": 2, 
    "tokens": [], 
    "entities": [
        {
            "salience": 0.30113336, 
            "mentions": [
                {
                    "text": {
                        "content": "Bamboo", 
                        "beginOffset": -1
                    }, 
                    "type": "PROPER"
                }, 
                {
                    "text": {
                        "content": "Bamboo", 
                        "beginOffset": -1
                    }, 
                    "type": "PROPER"
                }
            ], 
            "type": "OTHER", 
            "name": "Bamboo", 
            "metadata": {
                "mid": "/m/09qw8", 
                "wikipedia_url": "https://en.wikipedia.org/wiki/Bamboo"
            }
        }, 
        {
            "salience": 0.27120554, 
            "mentions": [
                {
                    "text": {
                        "content": "Semenyih", 
                        "beginOffset": -1
                    }, 
                    "type": "PROPER"
                }
            ], 
            "type": "LOCATION", 
            "name": "Semenyih", 
            "metadata": {
                "mid": "/m/058yg_", 
                "wikipedia_url": "https://en.wikipedia.org/wiki/Semenyih"
            }
        }, 
        {
            "salience": 0.08580879, 
            "mentions": [
                {
                    "text": {
                        "content": "eater.", 
                        "beginOffset": -1
                    }, 
                    "type": "COMMON"
                }
            ], 
            "type": "ORGANIZATION", 
            "name": "eater.", 
            "metadata": {}
        }, 
        {
            "salience": 0.06696404, 
            "mentions": [
                {
                    "text": {
                        "content": "Bamboo", 
                        "beginOffset": -1
                    }, 
                    "type": "COMMON"
                }
            ], 
            "type": "OTHER", 
            "name": "Bamboo", 
            "metadata": {}
        }, 
        {
            "salience": 0.05883437, 
            "mentions": [
                {
                    "text": {
                        "content": "walk", 
                        "beginOffset": -1
                    }, 
                    "type": "COMMON"
                }
            ], 
            "type": "OTHER", 
            "name": "walk", 
            "metadata": {}
        }, 
        {
            "salience": 0.058120936, 
            "mentions": [
                {
                    "text": {
                        "content": "playmate", 
                        "beginOffset": -1
                    }, 
                    "type": "COMMON"
                }
            ], 
            "type": "PERSON", 
            "name": "playmate", 
            "metadata": {}
        }, 
        {
            "salience": 0.045999087, 
            "mentions": [
                {
                    "text": {
                        "content": "hand", 
                        "beginOffset": -1
                    }, 
                    "type": "COMMON"
                }
            ], 
            "type": "OTHER", 
            "name": "hand", 
            "metadata": {}
        }, 
        {
            "salience": 0.039942577, 
            "mentions": [
                {
                    "text": {
                        "content": "food", 
                        "beginOffset": -1
                    }, 
                    "type": "COMMON"
                }
            ], 
            "type": "OTHER", 
            "name": "food", 
            "metadata": {}
        }, 
        {
            "salience": 0.028344817, 
            "mentions": [
                {
                    "text": {
                        "content": "Stop", 
                        "beginOffset": -1
                    }, 
                    "type": "COMMON"
                }
            ], 
            "type": "LOCATION", 
            "name": "Stop", 
            "metadata": {}
        }, 
        {
            "salience": 0.02253116, 
            "mentions": [
                {
                    "text": {
                        "content": "hand action", 
                        "beginOffset": -1
                    }, 
                    "type": "COMMON"
                }
            ], 
            "type": "OTHER", 
            "name": "hand action", 
            "metadata": {}
        }, 
        {
            "salience": 0.021115292, 
            "mentions": [
                {
                    "text": {
                        "content": "one", 
                        "beginOffset": -1
                    }, 
                    "type": "COMMON"
                }
            ], 
            "type": "OTHER", 
            "name": "one", 
            "metadata": {}
        }
    ], 
    "documentSentiment": {
        "magnitude": 1.1, 
        "score": 0.2
    }, 
    "sentences": [
        {
            "text": {
                "content": "Bamboo was found in Semenyih.", 
                "beginOffset": -1
            }, 
            "sentiment": {
                "magnitude": 0, 
                "score": 0
            }
        }, 
        {
            "text": {
                "content": "He is active, playful, brave and a big eater.If you're looking for a playmate or like to go for a slow walk,Bamboo is here for you.", 
                "beginOffset": -1
            }, 
            "sentiment": {
                "magnitude": 0.6, 
                "score": 0.6
            }
        }, 
        {
            "text": {
                "content": "We have trained Bamboo to do the hand action.", 
                "beginOffset": -1
            }, 
            "sentiment": {
                "magnitude": 0.3, 
                "score": 0.3
            }
        }, 
        {
            "text": {
                "content": "He will immediately seat and show you one of his hand when you say 'Stop' or when you holding his food.", 
                "beginOffset": -1
            }, 
            "sentiment": {
                "magnitude": 0.1, 
                "score": -0.1
            }
        }
    ], 
    "categories": []
}