{
    "language": "en", 
    "label": 4, 
    "tokens": [], 
    "entities": [
        {
            "salience": 0.63233197, 
            "mentions": [
                {
                    "text": {
                        "content": "Mimi", 
                        "beginOffset": -1
                    }, 
                    "type": "PROPER"
                }
            ], 
            "type": "PERSON", 
            "name": "Mimi", 
            "metadata": {}
        }, 
        {
            "salience": 0.08707346, 
            "mentions": [
                {
                    "text": {
                        "content": "start", 
                        "beginOffset": -1
                    }, 
                    "type": "COMMON"
                }
            ], 
            "type": "EVENT", 
            "name": "start", 
            "metadata": {}
        }, 
        {
            "salience": 0.08707346, 
            "mentions": [
                {
                    "text": {
                        "content": "life", 
                        "beginOffset": -1
                    }, 
                    "type": "COMMON"
                }
            ], 
            "type": "OTHER", 
            "name": "life", 
            "metadata": {}
        }, 
        {
            "salience": 0.084364496, 
            "mentions": [
                {
                    "text": {
                        "content": "age", 
                        "beginOffset": -1
                    }, 
                    "type": "COMMON"
                }
            ], 
            "type": "OTHER", 
            "name": "age", 
            "metadata": {}
        }, 
        {
            "salience": 0.042970978, 
            "mentions": [
                {
                    "text": {
                        "content": "eyelids", 
                        "beginOffset": -1
                    }, 
                    "type": "COMMON"
                }
            ], 
            "type": "OTHER", 
            "name": "eyelids", 
            "metadata": {}
        }, 
        {
            "salience": 0.023738, 
            "mentions": [
                {
                    "text": {
                        "content": "uterus", 
                        "beginOffset": -1
                    }, 
                    "type": "COMMON"
                }
            ], 
            "type": "OTHER", 
            "name": "uterus", 
            "metadata": {}
        }, 
        {
            "salience": 0.011663682, 
            "mentions": [
                {
                    "text": {
                        "content": "treatment", 
                        "beginOffset": -1
                    }, 
                    "type": "COMMON"
                }
            ], 
            "type": "OTHER", 
            "name": "treatment", 
            "metadata": {}
        }, 
        {
            "salience": 0.010920616, 
            "mentions": [
                {
                    "text": {
                        "content": "trauma", 
                        "beginOffset": -1
                    }, 
                    "type": "COMMON"
                }
            ], 
            "type": "OTHER", 
            "name": "trauma", 
            "metadata": {}
        }, 
        {
            "salience": 0.010710503, 
            "mentions": [
                {
                    "text": {
                        "content": "emergency spey", 
                        "beginOffset": -1
                    }, 
                    "type": "COMMON"
                }
            ], 
            "type": "OTHER", 
            "name": "emergency spey", 
            "metadata": {}
        }, 
        {
            "salience": 0.0056101657, 
            "mentions": [
                {
                    "text": {
                        "content": "health", 
                        "beginOffset": -1
                    }, 
                    "type": "COMMON"
                }
            ], 
            "type": "OTHER", 
            "name": "health", 
            "metadata": {}
        }, 
        {
            "salience": 0.0035426626, 
            "mentions": [
                {
                    "text": {
                        "content": "eyes", 
                        "beginOffset": -1
                    }, 
                    "type": "COMMON"
                }
            ], 
            "type": "OTHER", 
            "name": "eyes", 
            "metadata": {}
        }
    ], 
    "documentSentiment": {
        "magnitude": 2.3, 
        "score": 0
    }, 
    "sentences": [
        {
            "text": {
                "content": "Mimi had a hard start to life, she was raped at a very young age which progressed to having an infected uterus.", 
                "beginOffset": -1
            }, 
            "sentiment": {
                "magnitude": 0.8, 
                "score": -0.8
            }
        }, 
        {
            "text": {
                "content": "She had to have an emergency spey done and intensive treatment.", 
                "beginOffset": -1
            }, 
            "sentiment": {
                "magnitude": 0.1, 
                "score": 0.1
            }
        }, 
        {
            "text": {
                "content": "She has recovered in full since then but the trauma seems to have affected her eyes.", 
                "beginOffset": -1
            }, 
            "sentiment": {
                "magnitude": 0.1, 
                "score": 0.1
            }
        }, 
        {
            "text": {
                "content": "Her 3rd eyelids have never returned to normal since then; so they stick out.", 
                "beginOffset": -1
            }, 
            "sentiment": {
                "magnitude": 0.4, 
                "score": -0.4
            }
        }, 
        {
            "text": {
                "content": "She is otherwise in good health.", 
                "beginOffset": -1
            }, 
            "sentiment": {
                "magnitude": 0.6, 
                "score": 0.6
            }
        }
    ], 
    "categories": []
}