{
    "language": "en", 
    "label": 3, 
    "tokens": [], 
    "entities": [
        {
            "salience": 0.2887092, 
            "mentions": [
                {
                    "text": {
                        "content": "girl", 
                        "beginOffset": -1
                    }, 
                    "type": "COMMON"
                }
            ], 
            "type": "PERSON", 
            "name": "girl", 
            "metadata": {}
        }, 
        {
            "salience": 0.24971804, 
            "mentions": [
                {
                    "text": {
                        "content": "Oringa", 
                        "beginOffset": -1
                    }, 
                    "type": "PROPER"
                }, 
                {
                    "text": {
                        "content": "Boy", 
                        "beginOffset": -1
                    }, 
                    "type": "COMMON"
                }
            ], 
            "type": "PERSON", 
            "name": "Oringa", 
            "metadata": {}
        }, 
        {
            "salience": 0.21233483, 
            "mentions": [
                {
                    "text": {
                        "content": "Kittens: Twinky", 
                        "beginOffset": -1
                    }, 
                    "type": "PROPER"
                }
            ], 
            "type": "PERSON", 
            "name": "Kittens: Twinky", 
            "metadata": {}
        }, 
        {
            "salience": 0.08057854, 
            "mentions": [
                {
                    "text": {
                        "content": "adoption", 
                        "beginOffset": -1
                    }, 
                    "type": "COMMON"
                }
            ], 
            "type": "OTHER", 
            "name": "adoption", 
            "metadata": {}
        }, 
        {
            "salience": 0.06305447, 
            "mentions": [
                {
                    "text": {
                        "content": "Needs owner", 
                        "beginOffset": -1
                    }, 
                    "type": "COMMON"
                }
            ], 
            "type": "PERSON", 
            "name": "Needs owner", 
            "metadata": {}
        }, 
        {
            "salience": 0.04576547, 
            "mentions": [
                {
                    "text": {
                        "content": "Location", 
                        "beginOffset": -1
                    }, 
                    "type": "COMMON"
                }
            ], 
            "type": "LOCATION", 
            "name": "Location", 
            "metadata": {}
        }, 
        {
            "salience": 0.019294193, 
            "mentions": [
                {
                    "text": {
                        "content": "PAT", 
                        "beginOffset": -1
                    }, 
                    "type": "COMMON"
                }
            ], 
            "type": "OTHER", 
            "name": "PAT", 
            "metadata": {}
        }, 
        {
            "salience": 0.01631051, 
            "mentions": [
                {
                    "text": {
                        "content": "USJ 6", 
                        "beginOffset": -1
                    }, 
                    "type": "PROPER"
                }
            ], 
            "type": "ORGANIZATION", 
            "name": "USJ 6", 
            "metadata": {
                "mid": "/g/1w4vgf3h"
            }
        }, 
        {
            "salience": 0.0121173775, 
            "mentions": [
                {
                    "text": {
                        "content": "SMS", 
                        "beginOffset": -1
                    }, 
                    "type": "COMMON"
                }
            ], 
            "type": "OTHER", 
            "name": "SMS", 
            "metadata": {}
        }, 
        {
            "salience": 0.0121173775, 
            "mentions": [
                {
                    "text": {
                        "content": "Whatsapp", 
                        "beginOffset": -1
                    }, 
                    "type": "COMMON"
                }
            ], 
            "type": "OTHER", 
            "name": "Whatsapp", 
            "metadata": {}
        }
    ], 
    "documentSentiment": {
        "magnitude": 0.5, 
        "score": 0.1
    }, 
    "sentences": [
        {
            "text": {
                "content": "Two Kittens: Twinky(girl ) and Oringa(Boy) is for adoption.", 
                "beginOffset": -1
            }, 
            "sentiment": {
                "magnitude": 0.1, 
                "score": 0.1
            }
        }, 
        {
            "text": {
                "content": "Needs owner who can care for them well.", 
                "beginOffset": -1
            }, 
            "sentiment": {
                "magnitude": 0, 
                "score": 0
            }
        }, 
        {
            "text": {
                "content": "Please call/SMS or Whatsapp: Location:USJ 6 Thank You Ms. PAT", 
                "beginOffset": -1
            }, 
            "sentiment": {
                "magnitude": 0.2, 
                "score": 0.2
            }
        }
    ], 
    "categories": []
}