{
    "Fee": 0, 
    "sentences": [
        {
            "text": {
                "content": "Heyyyy Meet Snow !", 
                "beginOffset": -1
            }, 
            "sentiment": {
                "magnitude": 0.2, 
                "score": 0.2
            }
        }, 
        {
            "text": {
                "content": "She's 2 n half months old , she's a mix a breed, such a playful baby, active like no one's business , she loves jumping n playing with everything she can get hold off but she's an angel !", 
                "beginOffset": -1
            }, 
            "sentiment": {
                "magnitude": 0.4, 
                "score": 0.4
            }
        }, 
        {
            "text": {
                "content": "I would love to keep her..but due to some circumstances i have to give her away !", 
                "beginOffset": -1
            }, 
            "sentiment": {
                "magnitude": 0.7, 
                "score": 0.7
            }
        }, 
        {
            "text": {
                "content": "All she need someone to love her more n a new home..!", 
                "beginOffset": -1
            }, 
            "sentiment": {
                "magnitude": 0.8, 
                "score": 0.8
            }
        }, 
        {
            "text": {
                "content": "She is up for adoption !", 
                "beginOffset": -1
            }, 
            "sentiment": {
                "magnitude": 0, 
                "score": 0
            }
        }
    ], 
    "PhotoAmt": 1.0, 
    "Breed1": 307, 
    "Breed2": 0, 
    "MaturitySize": 2, 
    "Dewormed": 3, 
    "label": 4, 
    "Color1": 7, 
    "entities": [
        {
            "salience": 0.5042884, 
            "mentions": [
                {
                    "text": {
                        "content": "no one", 
                        "beginOffset": -1
                    }, 
                    "type": "COMMON"
                }, 
                {
                    "text": {
                        "content": "angel", 
                        "beginOffset": -1
                    }, 
                    "type": "COMMON"
                }
            ], 
            "type": "PERSON", 
            "name": "no one", 
            "metadata": {}
        }, 
        {
            "salience": 0.34446383, 
            "mentions": [
                {
                    "text": {
                        "content": "mix", 
                        "beginOffset": -1
                    }, 
                    "type": "COMMON"
                }, 
                {
                    "text": {
                        "content": "breed", 
                        "beginOffset": -1
                    }, 
                    "type": "COMMON"
                }
            ], 
            "type": "OTHER", 
            "name": "breed", 
            "metadata": {}
        }, 
        {
            "salience": 0.06332801, 
            "mentions": [
                {
                    "text": {
                        "content": "Snow", 
                        "beginOffset": -1
                    }, 
                    "type": "COMMON"
                }
            ], 
            "type": "OTHER", 
            "name": "Snow", 
            "metadata": {}
        }, 
        {
            "salience": 0.03842297, 
            "mentions": [
                {
                    "text": {
                        "content": "Heyyyy", 
                        "beginOffset": -1
                    }, 
                    "type": "PROPER"
                }
            ], 
            "type": "OTHER", 
            "name": "Heyyyy", 
            "metadata": {}
        }, 
        {
            "salience": 0.0094397, 
            "mentions": [
                {
                    "text": {
                        "content": "jumping n", 
                        "beginOffset": -1
                    }, 
                    "type": "COMMON"
                }
            ], 
            "type": "OTHER", 
            "name": "jumping n", 
            "metadata": {}
        }, 
        {
            "salience": 0.008299853, 
            "mentions": [
                {
                    "text": {
                        "content": "everything", 
                        "beginOffset": -1
                    }, 
                    "type": "COMMON"
                }
            ], 
            "type": "OTHER", 
            "name": "everything", 
            "metadata": {}
        }, 
        {
            "salience": 0.00819909, 
            "mentions": [
                {
                    "text": {
                        "content": "baby", 
                        "beginOffset": -1
                    }, 
                    "type": "COMMON"
                }
            ], 
            "type": "PERSON", 
            "name": "baby", 
            "metadata": {}
        }, 
        {
            "salience": 0.00819909, 
            "mentions": [
                {
                    "text": {
                        "content": "business", 
                        "beginOffset": -1
                    }, 
                    "type": "COMMON"
                }
            ], 
            "type": "OTHER", 
            "name": "business", 
            "metadata": {}
        }, 
        {
            "salience": 0.0048624747, 
            "mentions": [
                {
                    "text": {
                        "content": "someone", 
                        "beginOffset": -1
                    }, 
                    "type": "COMMON"
                }
            ], 
            "type": "PERSON", 
            "name": "someone", 
            "metadata": {}
        }, 
        {
            "salience": 0.003996203, 
            "mentions": [
                {
                    "text": {
                        "content": "home", 
                        "beginOffset": -1
                    }, 
                    "type": "COMMON"
                }
            ], 
            "type": "LOCATION", 
            "name": "home", 
            "metadata": {}
        }, 
        {
            "salience": 0.0039852783, 
            "mentions": [
                {
                    "text": {
                        "content": "adoption", 
                        "beginOffset": -1
                    }, 
                    "type": "COMMON"
                }
            ], 
            "type": "OTHER", 
            "name": "adoption", 
            "metadata": {}
        }, 
        {
            "salience": 0.0025151062, 
            "mentions": [
                {
                    "text": {
                        "content": "circumstances", 
                        "beginOffset": -1
                    }, 
                    "type": "COMMON"
                }
            ], 
            "type": "OTHER", 
            "name": "circumstances", 
            "metadata": {}
        }
    ], 
    "Color3": 0, 
    "Color2": 0, 
    "categories": [], 
    "Gender": 2, 
    "Age": 212, 
    "tokens": [], 
    "FurLength": 1, 
    "Quantity": 1, 
    "language": "en", 
    "Vaccinated": 3, 
    "documentSentiment": {
        "magnitude": 2.3, 
        "score": 0.4
    }, 
    "Sterilized": 2
}